[{"gender":"M","firstName":"Rafał","lastName":"Woźniak","age":72,"email":"rafał.woźniak@gmail.com","phone":"327780423"},{"gender":"M","firstName":"Krzysztof","lastName":"Wieczorek","age":26,"email":"krzysztof.wieczorek@gmail.com","phone":"638512123"},{"gender":"F","firstName":"Patrycja","lastName":"Woźniak","age":32,"email":"patrycja.woźniak@gmail.com","phone":"413074191"},{"gender":"M","firstName":"Przemysław","lastName":"Krawczyk","age":69,"email":"przemysław.krawczyk@gmail.com","phone":"274450678"},{"gender":"M","firstName":"Patryk","lastName":"Szymczak","age":98,"email":"patryk.szymczak@gmail.com","phone":"742877262"},{"gender":"M","firstName":"Grzegorz","lastName":"Wójcik","age":78,"email":"grzegorz.wójcik@gmail.com","phone":"459736842"},{"gender":"M","firstName":"Krzysztof","lastName":"Sikora","age":90,"email":"krzysztof.sikora@gmail.com","phone":"818364332"},{"gender":"F","firstName":"Julia","lastName":"Woźniak","age":51,"email":"julia.woźniak@gmail.com","phone":"889539313"},{"gender":"F","firstName":"Dorota","lastName":"Wieczorek","age":40,"email":"dorota.wieczorek@gmail.com","phone":"834481845"},{"gender":"M","firstName":"Krzysztof","lastName":"Zając","age":97,"email":"krzysztof.zając@gmail.com","phone":"553651546"},{"gender":"F","firstName":"Patrycja","lastName":"Wieczorek","age":41,"email":"patrycja.wieczorek@gmail.com","phone":"758786370"},{"gender":"F","firstName":"Magdalena","lastName":"Błaszczyk","age":40,"email":"magdalena.błaszczyk@gmail.com","phone":"444384922"},{"gender":"F","firstName":"Patrycja","lastName":"Woźniak","age":85,"email":"patrycja.woźniak@gmail.com","phone":"187493285"},{"gender":"M","firstName":"Rafał","lastName":"Błaszczyk","age":64,"email":"rafał.błaszczyk@gmail.com","phone":"167448138"},{"gender":"M","firstName":"Maciej","lastName":"Mróz","age":43,"email":"maciej.mróz@gmail.com","phone":"212512729"},{"gender":"M","firstName":"Mateusz","lastName":"Szymczak","age":73,"email":"mateusz.szymczak@gmail.com","phone":"632172617"},{"gender":"M","firstName":"Sebastian","lastName":"Błaszczyk","age":31,"email":"sebastian.błaszczyk@gmail.com","phone":"844997956"},{"gender":"F","firstName":"Klara","lastName":"Błaszczyk","age":89,"email":"klara.błaszczyk@gmail.com","phone":"936412873"},{"gender":"F","firstName":"Natalia","lastName":"Sikora","age":84,"email":"natalia.sikora@gmail.com","phone":"284951186"},{"gender":"M","firstName":"Paweł","lastName":"Woźniak","age":51,"email":"paweł.woźniak@gmail.com","phone":"365138312"}]